MANIFEST.in
README.rst
requirements.txt
setup.py
grabflickr/__init__.py
grabflickr/grabflickr.py
grabflickr.egg-info/PKG-INFO
grabflickr.egg-info/SOURCES.txt
grabflickr.egg-info/dependency_links.txt
grabflickr.egg-info/entry_points.txt
grabflickr.egg-info/requires.txt
grabflickr.egg-info/top_level.txt