Metadata-Version: 1.1
Name: grabflickr
Version: 0.0.2
Summary: Download photoset of flickr, support single process, multiprocess and gevent(Asynchronous I/O)
Home-page: https://github.com/carlcarl/grabflickr
Author: carlcarl
Author-email: carlcarlking@gmail.com
License: MIT
Platform: UNKNOWN
Classifier: Development Status :: 3 - Alpha
Classifier: Intended Audience :: End Users/Desktop
Classifier: License :: OSI Approved :: MIT License
Classifier: Programming Language :: Python
Classifier: Operating System :: MacOS :: MacOS X
Classifier: Operating System :: POSIX
Classifier: Operating System :: Unix
Classifier: Topic :: Utilities
Classifier: Topic :: Software Development :: Libraries
